prompt_defender/__init__.py
prompt_defender/core/__init__.py
prompt_defender/core/defence.py
prompt_defender/core/drawbridge_executor.py
prompt_defender/core/keep_executor.py
prompt_defender/core/wall_executor.py
prompt_defender/drawbridge/__init__.py
prompt_defender/drawbridge/default_drawbridge_executor.py
prompt_defender/keep/__init__.py
prompt_defender/keep/remote_keep.py
prompt_defender/tests/__init__.py
prompt_defender/tests/test_defence.py
prompt_defender/tests/test_drawbridge_executor.py
prompt_defender/tests/test_keep_executor.py
prompt_defender/tests/test_prompt_defender_client.py
prompt_defender/tests/test_prompt_validator.py
prompt_defender/tests/test_wall.py
prompt_defender/tests/test_xml_scanner.py
prompt_defender/wall/__init__.py
prompt_defender/wall/badwords_checker.py
prompt_defender/wall/prompt_defender_client.py
prompt_defender/wall/prompt_validator.py
prompt_defender/wall/wall_executor.py
prompt_defender/wall/xml_scanner.py
prompt_defender-0.1.26.dist-info/METADATA
prompt_defender-0.1.26.dist-info/WHEEL
prompt_defender-0.1.26.dist-info/RECORD
