Metadata-Version: 2.1
Name: prompt-defender
Version: 0.1.26
Summary: Prompt Defender. A package to help you defend against prompt injection attacks.
Author: Daniel Llewellyn
Author-email: admin@safetorun.com
Requires-Python: >=3.9,<4.0
Classifier: Programming Language :: Python :: 3
Classifier: Programming Language :: Python :: 3.9
Classifier: Programming Language :: Python :: 3.10
Classifier: Programming Language :: Python :: 3.11
Classifier: Programming Language :: Python :: 3.12
Requires-Dist: bleach (>=6.1.0,<7.0.0)
Requires-Dist: dataclasses-json (>=0.6.4,<0.7.0)
Requires-Dist: pydantic (>=2.6.3,<3.0.0)
Requires-Dist: requests (>=2.31.0,<3.0.0)
